Workbook

Sheet 销售收入预测
A1: 销售收入预测表
A2: 月/季/年 | C2: 1 | D2: 2 | E2: 3 | F2: 4 | G2: 5 | H2: 6 | I2: 7 | J2: 8 | K2: 9 | L2: 10 | M2: 11 | N2: 12 | O2: 合计
A3: 销售情况
A4: 产品或服务
A5: 简易小程序开发 | B5: 销售数量 | C5: 1 | D5: 1 | E5: 2 | F5: 2 | G5: 2 | H5: 3 | I5: 3 | J5: 4 | K5: 2 | L5: 2 | M5: 1 | N5: 1 | O5: =SUM(C5:N5) -> 24
B6: 平均单价 | C6: 3000 | D6: 3000 | E6: 3000 | F6: 3000 | G6: 3000 | H6: 3000 | I6: 3000 | J6: 3000 | K6: 3000 | L6: 3000 | M6: 3000 | N6: 3000 | O6: =SUM(C6:N6) -> 36000
B7: 月销售额 | C7: =C5*C6 -> 3000 | D7: =D5*D6 -> 3000 | E7: =E5*E6 -> 6000 | F7: =F5*F6 -> 6000 | G7: =G5*G6 -> 6000 | H7: =H5*H6 -> 9000 | I7: =I5*I6 -> 9000 | J7: =J5*J6 -> 12000 | ... N7: =N5*N6 -> 3000 | O7: =SUM(C7:N7) -> 72000
A8: 线下编程入门课程 | B8: 销售数量 | C8: 4 | D8: 3 | E8: 2 | F8: 2 | G8: 2 | H8: 4 | I8: 6 | J8: 5 | K8: 4 | L8: 4 | M8: 3 | N8: 2 | O8: =SUM(C8:N8) -> 41
B9: 平均单价 | C9: 1500 | D9: 1500 | E9: 1500 | F9: 1500 | G9: 1500 | H9: 1500 | I9: 1500 | J9: 1500 | K9: 1500 | L9: 1500 | M9: 1500 | N9: 1500 | O9: =SUM(C9:N9) -> 18000
B10: 月销售额 | C10: =C8*C9 -> 6000 | D10: =D8*D9 -> 4500 | E10: =E8*E9 -> 3000 | F10: =F8*F9 -> 3000 | G10: =G8*G9 -> 3000 | H10: =H8*H9 -> 6000 | I10: =I8*I9 -> 9000 | J10: =J8*J9 -> 7500 | ... N10: =N8*N9 -> 3000 | O10: =SUM(C10:N10) -> 61500
A11: 线上编程入门课程 | B11: 销售数量 | C11: 11 | D11: 9 | E11: 8 | F11: 7 | G11: 8 | H11: 9 | I11: 10 | J11: 11 | K11: 8 | L11: 8 | M11: 7 | N11: 8 | O11: =SUM(C11:N11) -> 104
B12: 平均单价 | C12: 600 | D12: 600 | E12: 600 | F12: 600 | G12: 600 | H12: 600 | I12: 600 | J12: 600 | K12: 600 | L12: 600 | M12: 600 | N12: 600 | O12: =SUM(C12:N12) -> 7200
B13: 月销售额 | C13: =C11*C12 -> 6600 | D13: =D11*D12 -> 5400 | E13: =E11*E12 -> 4800 | F13: =F11*F12 -> 4200 | G13: =G11*G12 -> 4800 | H13: =H11*H12 -> 5400 | I13: =I11*I12 -> 6000 | J13: =J11*J12 -> 6600 | ... N13: =N11*N12 -> 4800 | O13: =SUM(C13:N13) -> 62400
A14: 编程私教 | B14: 销售数量 | C14: 4 | D14: 4 | E14: 3 | F14: 3 | G14: 2 | H14: 4 | I14: 5 | J14: 5 | K14: 4 | L14: 3 | M14: 2 | N14: 2 | O14: =SUM(C14:N14) -> 41
B15: 平均单价 | C15: 1600 | D15: 1600 | E15: 1600 | F15: 1600 | G15: 1600 | H15: 1600 | I15: 1600 | J15: 1600 | K15: 1600 | L15: 1600 | M15: 1600 | N15: 1600 | O15: =SUM(C15:N15) -> 19200
B16: 月销售额 | C16: =C14*C15 -> 6400 | D16: =D14*D15 -> 6400 | E16: =E14*E15 -> 4800 | F16: =F14*F15 -> 4800 | G16: =G14*G15 -> 3200 | H16: =H14*H15 -> 6400 | I16: =I14*I15 -> 8000 | J16: =J14*J15 -> 8000 | ... N16: =N14*N15 -> 3200 | O16: =SUM(C16:N16) -> 65600
A17: 毕设/竞赛专项辅导 | B17: 销售数量 | C17: 3 | D17: 3 | E17: 2 | F17: 3 | G17: 4 | H17: 5 | I17: 4 | J17: 3 | K17: 3 | L17: 2 | M17: 2 | N17: 3 | O17: =SUM(C17:N17) -> 37
B18: 平均单价 | C18: 1500 | D18: 1500 | E18: 1500 | F18: 1500 | G18: 1500 | H18: 1500 | I18: 1500 | J18: 1500 | K18: 1500 | L18: 1500 | M18: 1500 | N18: 1500 | O18: =SUM(C18:N18) -> 18000
B19: 月销售额 | C19: =C17*C18 -> 4500 | D19: =D17*D18 -> 4500 | E19: =E17*E18 -> 3000 | F19: =F17*F18 -> 4500 | G19: =G17*G18 -> 6000 | H19: =H17*H18 -> 7500 | I19: =I17*I18 -> 6000 | J19: =J17*J18 -> 4500 | ... N19: =N17*N18 -> 4500 | O19: =SUM(C19:N19) -> 55500
A20: 定制化官网开发 | B20: 销售数量 | C20: 3 | D20: 2 | E20: 3 | F20: 3 | G20: 2 | H20: 3 | I20: 2 | J20: 3 | K20: 3 | L20: 2 | M20: 2 | N20: 2 | O20: =SUM(C20:N20) -> 30
B21: 平均单价 | C21: 6000 | D21: 6000 | E21: 6000 | F21: 6000 | G21: 6000 | H21: 6000 | I21: 6000 | J21: 6000 | K21: 6000 | L21: 6000 | M21: 6000 | N21: 6000 | O21: =SUM(C21:N21) -> 72000
B22: 月销售额 | C22: =C20*C21 -> 18000 | D22: =D20*D21 -> 12000 | E22: =E20*E21 -> 18000 | F22: =F20*F21 -> 18000 | G22: =G20*G21 -> 12000 | H22: =H20*H21 -> 18000 | I22: =I20*I21 -> 12000 | J22: =J20*J21 -> 18000 | ... N22: =N20*N21 -> 12000 | O22: =SUM(C22:N22) -> 180000
A23: 合 计 | B23: 销售总量 | C23: =C20+C17+C14+C11+C8+C5 -> 26 | D23: =D20+D17+D14+D11+D8+D5 -> 22 | E23: =E20+E17+E14+E11+E8+E5 -> 20 | F23: =F20+F17+F14+F11+F8+F5 -> 20 | G23: =G20+G17+G14+G11+G8+G5 -> 20 | H23: =H20+H17+H14+H11+H8+H5 -> 28 | I23: =I20+I17+I14+I11+I8+I5 -> 30 | J23: =J20+J17+J14+J11+J8+J5 -> 31 | ... O23: =O20+O17+O14+O11+O8+O5 -> 277
B24: 平均单价 | C24: =C25/C23 -> 1711.5385 | D24: =D25/D23 -> 1627.2727 | E24: =E25/E23 -> 1980 | F24: =F25/F23 -> 2025 | G24: =G25/G23 -> 1750 | H24: =H25/H23 -> 1867.8571 | I24: =I25/I23 -> 1666.6667 | J24: =J25/J23 -> 1825.8065 | ... O24: =O25/O23 -> 1794.2238
B25: 销售总收入 | C25: =C22+C19+C16+C13+C10+C7 -> 44500 | D25: =D22+D19+D16+D13+D10+D7 -> 35800 | E25: =E22+E19+E16+E13+E10+E7 -> 39600 | F25: =F22+F19+F16+F13+F10+F7 -> 40500 | G25: =G22+G19+G16+G13+G10+G7 -> 35000 | H25: =H22+H19+H16+H13+H10+H7 -> 52300 | I25: =I22+I19+I16+I13+I10+I7 -> 50000 | J25: =J22+J19+J16+J13+J10+J7 -> 56600 | ... O25: =O22+O19+O16+O13+O10+O7 -> 497000

Sheet 销售成本预测
A1: 销售成本与成本计划表
A2: 月/季/年 | C2: 1 | D2: 2 | E2: 3 | F2: 4 | G2: 5 | H2: 6 | I2: 7 | J2: 8 | K2: 9 | L2: 10 | M2: 11 | N2: 12 | O2: 合计
A3: 金额（元）
A4: 项目
A5: 销售 | B5: 含税销售收入 | C5: =销售收入预测!C25 -> 44500 | D5: =销售收入预测!D25 -> 35800 | E5: =销售收入预测!E25 -> 39600 | F5: =销售收入预测!F25 -> 40500 | G5: =销售收入预测!G25 -> 35000 | H5: =销售收入预测!H25 -> 52300 | I5: =销售收入预测!I25 -> 50000 | J5: =销售收入预测!J25 -> 56600 | ... N5: =销售收入预测!N25 -> 30500 | O5: =SUM(C5:N5) -> 497000
B6: 增值税 | C6: =IF(C5>150000,C5/1.03*0.03,0) -> 0 | D6: =IF(D5>150000,D5/1.03*0.03,0) -> 0 | E6: =IF(E5>150000,E5/1.03*0.03,0) -> 0 | F6: =IF(F5>150000,F5/1.03*0.03,0) -> 0 | G6: =IF(G5>150000,G5/1.03*0.03,0) -> 0 | H6: =IF(H5>150000,H5/1.03*0.03,0) -> 0 | I6: =IF(I5>150000,I5/1.03*0.03,0) -> 0 | J6: =IF(J5>150000,J5/1.03*0.03,0) -> 0 | ... N6: =IF(N5>150000,N5/1.03*0.03,0) -> 0 | O6: =SUM(C6:N6) -> 0
B7: 销售净收入 | C7: =C5-C6 -> 44500 | D7: =D5-D6 -> 35800 | E7: =E5-E6 -> 39600 | F7: =F5-F6 -> 40500 | G7: =G5-G6 -> 35000 | H7: =H5-H6 -> 52300 | I7: =I5-I6 -> 50000 | J7: =J5-J6 -> 56600 | ... N7: =N5-N6 -> 30500 | O7: =SUM(C7:N7) -> 497000
A8: 成本 | B8: 原材料 | C8: 0 | D8: =C8*销售收入预测!D23/销售收入预测!C23 -> 0 | E8: =D8*销售收入预测!E23/销售收入预测!D23 -> 0 | F8: =E8*销售收入预测!F23/销售收入预测!E23 -> 0 | G8: =F8*销售收入预测!G23/销售收入预测!F23 -> 0 | H8: =G8*销售收入预测!H23/销售收入预测!G23 -> 0 | I8: =H8*销售收入预测!I23/销售收入预测!H23 -> 0 | J8: =I8*销售收入预测!J23/销售收入预测!I23 -> 0 | K8: =J8*销售收入预测!K23/销售收入预测!J23 -> 0 | ... N8: =M8*销售收入预测!N23/销售收入预测!M23 -> 0 | O8: =SUM(C8:N8) -> 0
B9: 包装 | C9: =现金流量表!C13 -> 0 | D9: =现金流量表!D13 -> 0 | E9: =现金流量表!E13 -> 0 | F9: =现金流量表!F13 -> 0 | G9: =现金流量表!G13 -> 0 | H9: =现金流量表!H13 -> 0 | I9: =现金流量表!I13 -> 0 | J9: =现金流量表!J13 -> 0 | ... N9: =现金流量表!N13 -> 0 | O9: =SUM(C9:N9) -> 0
B10: 工资 | C10: 12000 | D10: 12000 | E10: 12000 | F10: 12000 | G10: 12000 | H10: 12000 | I10: 12000 | J10: 12000 | K10: 12000 | L10: 12000 | M10: 12000 | N10: 12000 | O10: =SUM(C10:N10) -> 144000
B11: 租金 | C11: 2000 | D11: 2000 | E11: 2000 | F11: 2000 | G11: 2000 | H11: 2000 | I11: 2000 | J11: 2000 | K11: 2000 | L11: 2000 | M11: 2000 | N11: 2000 | O11: =SUM(C11:N11) -> 24000
B12: 促销费 | C12: 1900 | D12: 1900 | E12: 1900 | F12: 1900 | G12: 1900 | H12: 1900 | I12: 1900 | J12: 1900 | K12: 1900 | L12: 1900 | M12: 1900 | N12: 1900 | O12: =SUM(C12:N12) -> 22800
B13: 保险费 | C13: 1500 | D13: 1500 | E13: 1500 | F13: 1500 | G13: 1500 | H13: 1500 | I13: 1500 | J13: 1500 | K13: 1500 | L13: 1500 | M13: 1500 | N13: 1500 | O13: =SUM(C13:N13) -> 18000
B14: 维修费 | C14: 500 | D14: 500 | E14: 500 | F14: 500 | G14: 500 | H14: 500 | I14: 500 | J14: 500 | K14: 500 | L14: 500 | M14: 500 | N14: 500 | O14: =SUM(C14:N14) -> 6000
B15: 水电费 | C15: 500 | D15: 500 | E15: 500 | F15: 500 | G15: 500 | H15: 500 | I15: 500 | J15: 500 | K15: 500 | L15: 500 | M15: 500 | N15: 500 | O15: =SUM(C15:N15) -> 6000
B16: 宽带费 | C16: 300 | D16: 300 | E16: 300 | F16: 300 | G16: 300 | H16: 300 | I16: 300 | J16: 300 | K16: 300 | L16: 300 | M16: 300 | N16: 300 | O16: =SUM(C16:N16) -> 3600
B17: 办公用品购置费 | C17: 500 | D17: 500 | E17: 500 | F17: 500 | G17: 500 | H17: 500 | I17: 500 | J17: 500 | K17: 500 | L17: 500 | M17: 500 | N17: 500 | O17: =SUM(C17:N17) -> 6000
B18: 其他费用 | C18: 0 | D18: =现金流量表!D26 -> 0 | E18: =现金流量表!E26 -> 0 | F18: =现金流量表!F26 -> 0 | G18: =现金流量表!G26 -> 0 | H18: =现金流量表!H26 -> 0 | I18: =现金流量表!I26 -> 0 | J18: =现金流量表!J26 -> 0 | K18: =现金流量表!K26 -> 0 | ... N18: =现金流量表!N26 -> 0 | O18: =SUM(C18:N18) -> 0
B19: 折旧和摊销 | C19: 530 | D19: =C19 -> 530 | E19: =D19 -> 530 | F19: =E19 -> 530 | G19: =F19 -> 530 | H19: =G19 -> 530 | I19: =H19 -> 530 | J19: =I19 -> 530 | K19: =J19 -> 530 | ... N19: =M19 -> 530 | O19: =SUM(C19:N19) -> 6360
B20: 总成本 | C20: =SUM(C9:C19)+C8 -> 19730 | D20: =SUM(D9:D19)+D8 -> 19730 | E20: =SUM(E9:E19)+E8 -> 19730 | F20: =SUM(F9:F19)+F8 -> 19730 | G20: =SUM(G9:G19)+G8 -> 19730 | H20: =SUM(H9:H19)+H8 -> 19730 | I20: =SUM(I9:I19)+I8 -> 19730 | J20: =SUM(J9:J19)+J8 -> 19730 | ... N20: =SUM(N9:N19)+N8 -> 19730 | O20: =SUM(C20:N20) -> 236760
A21: 附加税费 | C21: 0 | D21: 0 | E21: 0 | F21: 0 | G21: 0 | H21: 0 | I21: 0 | J21: 0 | K21: 0 | L21: 0 | M21: 0 | N21: 0 | O21: =SUM(C21:N21) -> 0
A22: 利 润 | C22: =C7-C20-C21 -> 24770 | D22: =D7-D20-D21 -> 16070 | E22: =E7-E20-E21 -> 19870 | F22: =F7-F20-F21 -> 20770 | G22: =G7-G20-G21 -> 15270 | H22: =H7-H20-H21 -> 32570 | I22: =I7-I20-I21 -> 30270 | J22: =J7-J20-J21 -> 36870 | ... N22: =N7-N20-N21 -> 10770 | O22: =SUM(C22:N22) -> 260240
A23: 所得税 | B23: 企业所得税 | C23: 0 | D23: 0 | E23: 0 | F23: 0 | G23: 0 | H23: 0 | I23: 0 | J23: 0 | K23: 0 | L23: 0 | M23: 0 | N23: 0 | O23: =SUM(C23:N23) -> 0
B24: 个人所得税 | O24: 41755.2
A25: 净利润 | C25: =C22 -> 24770 | D25: =D22 -> 16070 | E25: =E22 -> 19870 | F25: =F22 -> 20770 | G25: =G22 -> 15270 | H25: =H22 -> 32570 | I25: =I22 -> 30270 | J25: =J22 -> 36870 | ... N25: =N22 -> 10770 | O25: =O22-O23-O24 -> 218484.8

Sheet 现金流量表
A1: 现金流量表
A2: 月/季/年 | C2: 1 | D2: 2 | E2: 3 | F2: 4 | G2: 5 | H2: 6 | I2: 7 | J2: 8 | K2: 9 | L2: 10 | M2: 11 | N2: 12 | O2: 合计
A3: 金额（元）
A4: 项目
A5: 月初现金（A） | C5: 0 | D5: =C28 -> 2300 | E5: =D28 -> 18900 | F5: =E28 -> 39300 | G5: =F28 -> 60600 | H5: =G28 -> 76400 | I5: =H28 -> 109500 | J5: =I28 -> 140300 | K5: =J28 -> 177700 | ... N5: =M28 -> 232300
A6: 现金流入 | B6: 现金销售收入 | C6: =销售收入预测!C25 -> 44500 | D6: =销售收入预测!D25 -> 35800 | E6: =销售收入预测!E25 -> 39600 | F6: =销售收入预测!F25 -> 40500 | G6: =销售收入预测!G25 -> 35000 | H6: =销售收入预测!H25 -> 52300 | I6: =销售收入预测!I25 -> 50000 | J6: =销售收入预测!J25 -> 56600 | ... N6: =销售收入预测!N25 -> 30500 | O6: =SUM(C6:N6) -> 497000
B7: 赊销销售收入 | C7: 0 | D7: 0 | E7: 0 | F7: 0 | G7: 0 | H7: 0 | I7: 0 | J7: 0 | K7: 0 | L7: 0 | M7: 0 | N7: 0 | O7: =SUM(C7:N7) -> 0
B8: 贷款 | C8: 0 | D8: 0 | E8: 0 | F8: 0 | G8: 0 | H8: 0 | I8: 0 | J8: 0 | K8: 0 | L8: 0 | M8: 0 | N8: 0 | O8: =SUM(C8:N8) -> 0
B9: 企业主（股东）投资 | C9: 0 | D9: 0 | E9: 0 | F9: 0 | G9: 0 | H9: 0 | I9: 0 | J9: 0 | K9: 0 | L9: 0 | M9: 0 | N9: 0 | O9: =SUM(C9:N9) -> 0
B10: 现金流入合计（B） | C10: =SUM(C6:C9) -> 44500 | D10: =SUM(D6:D9) -> 35800 | E10: =SUM(E6:E9) -> 39600 | F10: =SUM(F6:F9) -> 40500 | G10: =SUM(G6:G9) -> 35000 | H10: =SUM(H6:H9) -> 52300 | I10: =SUM(I6:I9) -> 50000 | J10: =SUM(J6:J9) -> 56600 | ... N10: =SUM(N6:N9) -> 30500 | O10: =SUM(C10:N10) -> 497000
A11: 现金流出 | B11: 现金采购 | C11: =销售成本预测!C8 -> 0 | D11: =销售成本预测!D8 -> 0 | E11: =销售成本预测!E8 -> 0 | F11: =销售成本预测!F8 -> 0 | G11: =销售成本预测!G8 -> 0 | H11: =销售成本预测!H8 -> 0 | I11: =销售成本预测!I8 -> 0 | J11: =销售成本预测!J8 -> 0 | ... N11: =销售成本预测!N8 -> 0 | O11: =SUM(C11:N11) -> 0
B12: 赊账采购 | C12: 0 | D12: 0 | E12: 0 | F12: 0 | G12: 0 | H12: 0 | I12: 0 | J12: 0 | K12: 0 | L12: 0 | M12: 0 | N12: 0 | O12: =SUM(C12:N12) -> 0
B13: 包装费 | C13: 0 | D13: 0 | E13: 0 | F13: 0 | G13: 0 | H13: 0 | I13: 0 | J13: 0 | K13: 0 | L13: 0 | M13: 0 | N13: 0 | O13: =SUM(C13:N13) -> 0
B14: 工资 | C14: 12000 | D14: 12000 | E14: 12000 | F14: 12000 | G14: 12000 | H14: 12000 | I14: 12000 | J14: 12000 | K14: 12000 | L14: 12000 | M14: 12000 | N14: 12000 | O14: =SUM(C14:N14) -> 144000
B15: 租金 | C15: 2000 | D15: 2000 | E15: 2000 | F15: 2000 | G15: 2000 | H15: 2000 | I15: 2000 | J15: 2000 | K15: 2000 | L15: 2000 | M15: 2000 | N15: 2000 | O15: =SUM(C15:N15) -> 24000
B16: 促销费 | C16: 1900 | D16: 1900 | E16: 1900 | F16: 1900 | G16: 1900 | H16: 1900 | I16: 1900 | J16: 1900 | K16: 1900 | L16: 1900 | M16: 1900 | N16: 1900 | O16: =SUM(C16:N16) -> 22800
B17: 保险费 | C17: 1500 | D17: 1500 | E17: 1500 | F17: 1500 | G17: 1500 | H17: 1500 | I17: 1500 | J17: 1500 | K17: 1500 | L17: 1500 | M17: 1500 | N17: 1500 | O17: =SUM(C17:N17) -> 18000
B18: 维修费 | C18: 500 | D18: 500 | E18: 500 | F18: 500 | G18: 500 | H18: 500 | I18: 500 | J18: 500 | K18: 500 | L18: 500 | M18: 500 | N18: 500 | O18: =SUM(C18:N18) -> 6000
B19: 水电费 | C19: 500 | D19: 500 | E19: 500 | F19: 500 | G19: 500 | H19: 500 | I19: 500 | J19: 500 | K19: 500 | L19: 500 | M19: 500 | N19: 500 | O19: =SUM(C19:N19) -> 6000
B20: 宽带费 | C20: 300 | D20: 300 | E20: 300 | F20: 300 | G20: 300 | H20: 300 | I20: 300 | J20: 300 | K20: 300 | L20: 300 | M20: 300 | N20: 300 | O20: =SUM(C20:N20) -> 3600
B21: 办公用品购置费 | C21: 500 | D21: 500 | E21: 500 | F21: 500 | G21: 500 | H21: 500 | I21: 500 | J21: 500 | K21: 500 | L21: 500 | M21: 500 | N21: 500 | O21: =SUM(C21:N21) -> 6000
B22: 贷款本息 | C22: 0 | D22: 0 | E22: 0 | F22: 0 | G22: 0 | H22: 0 | I22: 0 | J22: 0 | K22: 0 | L22: 0 | M22: 0 | N22: 0 | O22: 0
B23: 税金 | C23: 0 | D23: 0 | E23: 0 | F23: 0 | G23: 0 | H23: 0 | I23: 0 | J23: 0 | K23: 0 | L23: 0 | M23: 0 | N23: 0 | O23: 0
B24: 固定资产投资 | C24: 22350 | D24: 0 | E24: 0 | F24: 0 | G24: 0 | H24: 0 | I24: 0 | J24: 0 | K24: 0 | L24: 0 | M24: 0 | N24: 0 | O24: =SUM(C24:N24) -> 22350
B25: 开办费 | C25: 650 | D25: 0 | E25: 0 | F25: 0 | G25: 0 | H25: 0 | I25: 0 | J25: 0 | K25: 0 | L25: 0 | M25: 0 | N25: 0 | O25: =SUM(C25:N25) -> 650
B26: 其他投入 | C26: 0 | D26: 0 | E26: 0 | F26: 0 | G26: 0 | H26: 0 | I26: 0 | J26: 0 | K26: 0 | L26: 0 | M26: 0 | N26: 0 | O26: =SUM(C26:N26) -> 0
B27: 现金流出合计（C） | C27: =SUM(C11:C26) -> 42200 | D27: =SUM(D11:D26) -> 19200 | E27: =SUM(E11:E26) -> 19200 | F27: =SUM(F11:F26) -> 19200 | G27: =SUM(G11:G26) -> 19200 | H27: =SUM(H11:H26) -> 19200 | I27: =SUM(I11:I26) -> 19200 | J27: =SUM(J11:J26) -> 19200 | ... N27: =SUM(N11:N26) -> 19200 | O27: =SUM(C27:N27) -> 253400
A28: 月底现金(A+B-C) | C28: =C5+C10-C27 -> 2300 | D28: =D5+D10-D27 -> 18900 | E28: =E5+E10-E27 -> 39300 | F28: =F5+F10-F27 -> 60600 | G28: =G5+G10-G27 -> 76400 | H28: =H5+H10-H27 -> 109500 | I28: =I5+I10-I27 -> 140300 | J28: =J5+J10-J27 -> 177700 | ... N28: =N5+N10-N27 -> 243600
